paux/__init__.py
paux/date.py
paux/digit.py
paux/file.py
paux/filter.py
paux/log.py
paux/order.py
paux/param.py
paux/process.py
paux/system.py
paux/thread.py
paux/exception/__init__.py
paux/exception/_base.py
paux/exception/execute.py
paux/exception/param.py
paux-1.0.14.dist-info/METADATA
paux-1.0.14.dist-info/WHEEL
paux-1.0.14.dist-info/top_level.txt
paux-1.0.14.dist-info/RECORD
